pygwan2/__init__.py
pygwan2/pygwan2.py
pygwan2-0.1.dist-info/LICENCE
pygwan2-0.1.dist-info/METADATA
pygwan2-0.1.dist-info/WHEEL
pygwan2-0.1.dist-info/top_level.txt
pygwan2-0.1.dist-info/RECORD
