Metadata-Version: 2.1
Name: pygwan2
Version: 0.1
Summary: since i lost the original package, i am trying to create a new one.
Home-page: https://github.com/lordskyzw/pygwan2
Author: Tarmica Sean Chiwara
Author-email: tarimicac+pypi@gmail.com
License: MIT
License-File: LICENCE
Requires-Dist: requests >=2.25.0
Requires-Dist: colorama >=0.4.3
Requires-Dist: requests-toolbelt >=0.9.1
